{"dependencies":[{"name":"/Volumes/Work/forks/til.camp/package.json","includedInParent":true,"mtime":1526468255000},{"name":"/Volumes/Work/forks/til.camp/.browserslistrc","includedInParent":true,"mtime":1524300285000},{"name":"/Volumes/Work/forks/til.camp/node_modules/@firebase/database/package.json","includedInParent":true,"mtime":1519337717000},{"name":"./SortedMap","loc":{"line":18,"column":26}},{"name":"./Path","loc":{"line":19,"column":21}},{"name":"./util","loc":{"line":20,"column":21}},{"name":"@firebase/util","loc":{"line":21,"column":21}}],"generated":{"js":"\"use strict\";Object.defineProperty(exports,\"__esModule\",{value:!0});var t,e=require(\"./SortedMap\"),r=require(\"./Path\"),n=require(\"./util\"),i=require(\"@firebase/util\"),o=function(){return t||(t=new e.SortedMap(n.stringCompare)),t},h=function(){function t(t,e){void 0===e&&(e=o()),this.value=t,this.children=e}return t.fromObject=function(e){var n=t.Empty;return i.forEach(e,function(t,e){n=n.set(new r.Path(t),e)}),n},t.prototype.isEmpty=function(){return null===this.value&&this.children.isEmpty()},t.prototype.findRootMostMatchingPathAndValue=function(t,e){if(null!=this.value&&e(this.value))return{path:r.Path.Empty,value:this.value};if(t.isEmpty())return null;var n=t.getFront(),i=this.children.get(n);if(null!==i){var o=i.findRootMostMatchingPathAndValue(t.popFront(),e);return null!=o?{path:new r.Path(n).child(o.path),value:o.value}:null}return null},t.prototype.findRootMostValueAndPath=function(t){return this.findRootMostMatchingPathAndValue(t,function(){return!0})},t.prototype.subtree=function(e){if(e.isEmpty())return this;var r=e.getFront(),n=this.children.get(r);return null!==n?n.subtree(e.popFront()):t.Empty},t.prototype.set=function(e,r){if(e.isEmpty())return new t(r,this.children);var n=e.getFront(),i=(this.children.get(n)||t.Empty).set(e.popFront(),r),o=this.children.insert(n,i);return new t(this.value,o)},t.prototype.remove=function(e){if(e.isEmpty())return this.children.isEmpty()?t.Empty:new t(null,this.children);var r=e.getFront(),n=this.children.get(r);if(n){var i=n.remove(e.popFront()),o=void 0;return o=i.isEmpty()?this.children.remove(r):this.children.insert(r,i),null===this.value&&o.isEmpty()?t.Empty:new t(this.value,o)}return this},t.prototype.get=function(t){if(t.isEmpty())return this.value;var e=t.getFront(),r=this.children.get(e);return r?r.get(t.popFront()):null},t.prototype.setTree=function(e,r){if(e.isEmpty())return r;var n=e.getFront(),i=(this.children.get(n)||t.Empty).setTree(e.popFront(),r),o=void 0;return o=i.isEmpty()?this.children.remove(n):this.children.insert(n,i),new t(this.value,o)},t.prototype.fold=function(t){return this.fold_(r.Path.Empty,t)},t.prototype.fold_=function(t,e){var r={};return this.children.inorderTraversal(function(n,i){r[n]=i.fold_(t.child(n),e)}),e(t,this.value,r)},t.prototype.findOnPath=function(t,e){return this.findOnPath_(t,r.Path.Empty,e)},t.prototype.findOnPath_=function(t,e,r){var n=!!this.value&&r(e,this.value);if(n)return n;if(t.isEmpty())return null;var i=t.getFront(),o=this.children.get(i);return o?o.findOnPath_(t.popFront(),e.child(i),r):null},t.prototype.foreachOnPath=function(t,e){return this.foreachOnPath_(t,r.Path.Empty,e)},t.prototype.foreachOnPath_=function(e,r,n){if(e.isEmpty())return this;this.value&&n(r,this.value);var i=e.getFront(),o=this.children.get(i);return o?o.foreachOnPath_(e.popFront(),r.child(i),n):t.Empty},t.prototype.foreach=function(t){this.foreach_(r.Path.Empty,t)},t.prototype.foreach_=function(t,e){this.children.inorderTraversal(function(r,n){n.foreach_(t.child(r),e)}),this.value&&e(t,this.value)},t.prototype.foreachChild=function(t){this.children.inorderTraversal(function(e,r){r.value&&t(e,r.value)})},t.Empty=new t(null),t}();exports.ImmutableTree=h;"},"hash":"51cc465de32539dbbe076c1e2e213c07","cacheData":{"env":{}}}