{"dependencies":[{"name":"/Volumes/Work/forks/til.camp/package.json","includedInParent":true,"mtime":1526468255000},{"name":"/Volumes/Work/forks/til.camp/.browserslistrc","includedInParent":true,"mtime":1524300285000},{"name":"/Volumes/Work/forks/til.camp/node_modules/@firebase/util/package.json","includedInParent":true,"mtime":1519337717000},{"name":"./obj","loc":{"line":18,"column":20}}],"generated":{"js":"\"use strict\";Object.defineProperty(exports,\"__esModule\",{value:!0});var e=require(\"./obj\");exports.querystring=function(n){var o=[];return e.forEach(n,function(e,n){Array.isArray(n)?n.forEach(function(n){o.push(encodeURIComponent(e)+\"=\"+encodeURIComponent(n))}):o.push(encodeURIComponent(e)+\"=\"+encodeURIComponent(n))}),o.length?\"&\"+o.join(\"&\"):\"\"},exports.querystringDecode=function(e){var n={};return e.replace(/^\\?/,\"\").split(\"&\").forEach(function(e){if(e){var o=e.split(\"=\");n[o[0]]=o[1]}}),n};"},"hash":"442049d421813f075eff826629d26780","cacheData":{"env":{}}}