{"dependencies":[{"name":"/Volumes/Work/forks/til.camp/package.json","includedInParent":true,"mtime":1526468255000},{"name":"/Volumes/Work/forks/til.camp/.browserslistrc","includedInParent":true,"mtime":1524300285000},{"name":"/Volumes/Work/forks/til.camp/node_modules/@firebase/database/package.json","includedInParent":true,"mtime":1519337717000},{"name":"./StatsCollection","loc":{"line":18,"column":32}}],"generated":{"js":"\"use strict\";Object.defineProperty(exports,\"__esModule\",{value:!0});var t=require(\"./StatsCollection\"),e=function(){function e(){}return e.getCollection=function(e){var r=e.toString();return this.collections_[r]||(this.collections_[r]=new t.StatsCollection),this.collections_[r]},e.getOrCreateReporter=function(t,e){var r=t.toString();return this.reporters_[r]||(this.reporters_[r]=e()),this.reporters_[r]},e.collections_={},e.reporters_={},e}();exports.StatsManager=e;"},"hash":"b74334bad1a65d562dd7237cd7a74124","cacheData":{"env":{}}}